setup.cfg
setup.py
qqbot/__init__.py
qqbot/__main__.py
qqbot/basicqsession.py
qqbot/common.py
qqbot/facemap.py
qqbot/groupmanager.py
qqbot/mailagent.py
qqbot/mainloop.py
qqbot/mysocketserver.py
qqbot/qconf.py
qqbot/qqbotcls.py
qqbot/qrcodemanager.py
qqbot/qrcodeserver.py
qqbot/qsession.py
qqbot/qterm.py
qqbot/termbot.py
qqbot/utf8logger.py
qqbot.egg-info/PKG-INFO
qqbot.egg-info/SOURCES.txt
qqbot.egg-info/dependency_links.txt
qqbot.egg-info/entry_points.txt
qqbot.egg-info/requires.txt
qqbot.egg-info/top_level.txt
qqbot/plugins/__init__.py
qqbot/plugins/addqqcmd.py
qqbot/plugins/miniirc.py
qqbot/plugins/passwordlogin.py
qqbot/plugins/sample.py
qqbot/plugins/sampleslots.py
qqbot/plugins/schedrestart.py
qqbot/qcontactdb/__init__.py
qqbot/qcontactdb/contactdb.py
qqbot/qcontactdb/display.py
qqbot/qcontactdb/fetch.py
qqbot/qcontactdb/getgroupqq.py
qqbot/qcontactdb/myprettytable.py
qqbot/qcontactdb/qcontactdb.py
qqbot/qcontactdb/tmp-qcontactdb--new.py