Metadata-Version: 1.1
Name: qqbot
Version: 2.3.9
Summary: QQBot: A conversation robot base on Tencent's SmartQQ
Home-page: https://github.com/pandolia/qqbot/
Author: pandolia
Author-email: pandolia@yeah.net
License: UNKNOWN
Download-URL: https://github.com/pandolia/qqbot/archive/v2.3.9.tar.gz
Keywords: QQBot,conversation robot,tencent,qq,web,network,python,http
Platform: UNKNOWN
